ln2sqlmodule/Column.py
ln2sqlmodule/Database.py
ln2sqlmodule/Exception.py
ln2sqlmodule/Generator.py
ln2sqlmodule/LangConfig.py
ln2sqlmodule/Parser.py
ln2sqlmodule/ParsingException.py
ln2sqlmodule/Query.py
ln2sqlmodule/StopwordFilter.py
ln2sqlmodule/Table.py
ln2sqlmodule/Thesaurus.py
ln2sqlmodule/__init__.py
ln2sqlmodule/ln2sql.py
ln2sqlmodule/settings.py
ln2sqlmodule/unitTests.py
ln2sqlmodule/lang/english.csv
ln2sqlmodule/lang/french.csv
ln2sqlmodule/lang/perso.csv
ln2sqlmodule/stopwords/english.txt
ln2sqlmodule/stopwords/french.txt
ln2sqlmodule/stopwords/german.txt
ln2sqlmodule/stopwords/italian.txt
ln2sqlmodule/stopwords/spain.txt
ln2sqlmodule/thesaurus/th_english.dat
ln2sqlmodule/thesaurus/th_french.dat
ln2sqlmodule/thesaurus/th_german.dat
ln2sqlmodule/thesaurus/th_italian.dat
ln2sqlmodule-1.0.2.dist-info/LICENSE.txt
ln2sqlmodule-1.0.2.dist-info/METADATA
ln2sqlmodule-1.0.2.dist-info/WHEEL
ln2sqlmodule-1.0.2.dist-info/top_level.txt
ln2sqlmodule-1.0.2.dist-info/RECORD
